HISTORY.txt
MANIFEST.in
README.txt
setup.cfg
setup.py
src/megrok/__init__.py
src/megrok.scaffold.egg-info/PKG-INFO
src/megrok.scaffold.egg-info/SOURCES.txt
src/megrok.scaffold.egg-info/dependency_links.txt
src/megrok.scaffold.egg-info/entry_points.txt
src/megrok.scaffold.egg-info/namespace_packages.txt
src/megrok.scaffold.egg-info/not-zip-safe
src/megrok.scaffold.egg-info/requires.txt
src/megrok.scaffold.egg-info/top_level.txt
src/megrok/scaffold/README.txt
src/megrok/scaffold/__init__.py
src/megrok/scaffold/components.py
src/megrok/scaffold/configure.zcml
src/megrok/scaffold/directive.py
src/megrok/scaffold/forms.py
src/megrok/scaffold/i18n.py
src/megrok/scaffold/interfaces.py
src/megrok/scaffold/meta.py
src/megrok/scaffold/meta.zcml
src/megrok/scaffold/templates/default_display_form.pt
src/megrok/scaffold/templates/default_edit_form.pt
src/megrok/scaffold/templates/default_list_form.pt
src/megrok/scaffold/tests/__init__.py
src/megrok/scaffold/tests/ftesting.zcml
src/megrok/scaffold/tests/test_all.py