Metadata-Version: 1.0
Name: megrok.scaffold
Version: 0.3
Summary: Auto-generate CRUD forms for a given domain class.
Home-page: http://pypi.python.org/pypi/megrok.scaffold
Author: Danilo G. Botelho
Author-email: danilogbotelho@yahoo.com
License: GPL
Keywords: CRUD form auto model scaffold
Platform: UNKNOWN
Classifier: Programming Language :: Python
Classifier: Development Status :: 4 - Beta
Classifier: Environment :: Web Environment
Classifier: Intended Audience :: Developers
Classifier: Natural Language :: English
Classifier: Operating System :: OS Independent
Classifier: Topic :: Internet :: WWW/HTTP
Classifier: Framework :: Zope3
